asgi_replay.py
asgi_replay-0.1a0.dist-info/METADATA
asgi_replay-0.1a0.dist-info/WHEEL
asgi_replay-0.1a0.dist-info/entry_points.txt
asgi_replay-0.1a0.dist-info/top_level.txt
asgi_replay-0.1a0.dist-info/RECORD
