Metadata-Version: 2.1
Name: asgi-replay
Version: 0.1a0
Summary: Record and replay ASGI web page loads
Author: Simon Willison
License: Apache-2.0
Project-URL: Homepage, https://github.com/simonw/asgi-replay
Project-URL: Changelog, https://github.com/simonw/asgi-replay/releases
Project-URL: Issues, https://github.com/simonw/asgi-replay/issues
Project-URL: CI, https://github.com/simonw/asgi-replay/actions
Requires-Dist: asgi-proxy-lib
Requires-Dist: click
Requires-Dist: uvicorn
